gitrepos/i2c_protocol/i2c_master.v

module i2c_master(
  input clk,rd_wr,start,stop,reset,
  input [6:0] address,
  input [7:0] din,
  inout SDA,
  output SCL,
  output reg [7:0] dout
);
  reg [3:0] state ;
  parameter S0 = 0, S1 = 1, S2 = 2 , S3 = 3, S4 =4 , S5 = 5 , S6 = 6, S7 = 7, S8 = 8, S9 = 9,S10 = 10, S11 = 11, S12 = 12,S13 = 13, S14 = 14 ,sender_mode = 1,receiver_mode = 0,address_phase = 0,data_phase = 1;
  reg [2:0] count;
  reg scl , sda,ack,mode;
   reg [7:0] tx_reg;
  
 
  
  ////////////////////////////////////
  
  always @(posedge clk ) begin
    
    if (reset) begin
      count <= 0;
      state <= S0;
      
      scl   <= 1;
      sda   <= 1;
      dout  <= 0;
    end
  
  else  
    
    case (state) 
      
      S0 : begin
        if (start == 1'b1) 
          state <= S1 ;
          else state <= S0;
        scl <= 1;
        sda <= 1;
      
      end
      
      S1 : begin
        state <= S2;
        sda <= 0;
        count <= 0;
        mode <= rd_wr; // read or write status must be maintained by user at rd_wr pin
        tx_reg <= {address,rd_wr};
       
      	end
        
      S2 : begin
        scl <= 0; // falling edge by master
        state <= S3;
        sda <= tx_reg[~count] ;
         
        
      end
      
      S3 : begin
	        scl <= 1;// rising edge by master 
        count <= count +1;
        if (count == 0) state <= S4;
        else state <= S2;
      end

               
           
     
      
	  S4 : begin
        state <= S5;
        scl <= 0; // negedge scl
        
      end
      
      S5 : begin
        scl <= 1; //rising edge
        
        if(SDA == 0) ack <= 1;
        else ack <= 0;
        
       	 if(ack == 0) state <= S0;
       	 else begin
         	
           if(ack == 1 && mode == receiver_mode) begin
           	 state <= S8;
          	  tx_reg <= 0;
        	  end
         
         	 if(ack == 1 && mode == sender_mode) begin
          	  state <= S6;
          	  tx_reg <= din;
        	  end
//in place of ack SDA can be directly used here to check
       end
      end

      
      S6 : begin
            scl <= 0; // negedge scl
        if(count == 0 && stop == 1) begin //for stop detection
          	state <= S13;
        	  sda <= 0;
        	end
        	else begin
          	state <= S7;
          	sda <= tx_reg[~count];
      	  	end
        
      	end
      
      S7 : begin
        
        scl <= 1; //posedge scl
        count <= count +1;
        if(count == 0)state <= S4;
        else state <= S6;
        
      end
      
      S8 : begin
        scl <= 0; // negedge scl
        sda<=1;/////edited	
        if(stop == 1)begin
          	state <= S13;
          		sda <= 0;
        	end
        else state <= S9;
               
      end
        
        
      S9 : begin
        scl <= 1; // posedge scl
        tx_reg[~count] <= SDA;
        if(count == 7) state <=S11;
        else state <= S10;
        
      end
      
      S10 : begin
        scl <= 0 ; // negedge scl
        count <= count +1;
        state <= S9;
                
      end

      S11 : begin
        scl <= 0 ; // negedge scl
        sda <= 0;
        count <= 0;
        state <= S12;
      end

      S12 : begin
        scl <= 1; // posedge scl
        dout <= tx_reg;
        state <= S8;
        
      end
      
      S13 : begin
         scl <= 1; // posedge scl
        state <= S14;
        
      end

      
      S14 : begin
        //stop
        sda <= 1;
        state <= S0;
        
      end

    endcase
   
  end
          
  assign SDA = (sda == 0 ) ? 1'b0 : 1'b1 ;
  assign SCL = (scl == 0 ) ? 1'b0 : 1'b1 ;
      
  
endmodule

gitrepos/i2c_protocol/i2c_tb.v

module test_i2c_master();
  reg     clk_tb, rd_wr_tb, start_tb, stop_tb, reset_tb;
  reg     [6:0] address_tb;
  reg     [7:0] din_tb;
  wire    SDA_tb;
  wire    SCL_tb;
  wire    [7:0] dout_tb;

i2c_master dut (
  .clk(clk_tb),
  .rd_wr(rd_wr_tb),
  .start(start_tb),
  .stop(stop_tb),
  .reset(reset_tb),
  .address(address_tb),
  .din(din_tb),
  .SDA(SDA_tb),
  .SCL(SCL_tb),
  .dout(dout_tb)
);

  //DUMPS
  initial begin
    $dumpfile("i2c.vcd");
    $dumpvars(0, test_i2c_master);
    
    #1000 $finish;
  end

  // CLOCK GENERATION
  initial begin
    forever begin
      #5 clk_tb = ~clk_tb;
    end
  end

  // INITIALIZING VALUES
  initial begin
    clk_tb      = 1'b0; 
    rd_wr_tb    = 1'b0; 
    start_tb    = 1'b0; 
    stop_tb     = 1'b0; 
    reset_tb    = 1'b0;
    address_tb  = 7'b0;
    din_tb      = 8'b0;
  end

  initial begin
    #10 reset_tb    = 1'b1;
    #10 reset_tb    = 1'b0;
    #10 start_tb    = 1'b1;
        rd_wr_tb    = 1'b1;
        address_tb  = 7'b1101;
        din_tb      = 8'b10010;
  end



endmodule

gitrepos/i2c_protocol/i2c.vcd
$date
	Thu Nov 16 13:13:19 2023
$end
$version
	Icarus Verilog
$end
$timescale
	1s
$end
$scope module test_i2c_master $end
$var wire 8 ! dout_tb [7:0] $end
$var wire 1 " SDA_tb $end
$var wire 1 # SCL_tb $end
$var reg 7 $ address_tb [6:0] $end
$var reg 1 % clk_tb $end
$var reg 8 & din_tb [7:0] $end
$var reg 1 ' rd_wr_tb $end
$var reg 1 ( reset_tb $end
$var reg 1 ) start_tb $end
$var reg 1 * stop_tb $end
$scope module dut $end
$var wire 7 + address [6:0] $end
$var wire 1 % clk $end
$var wire 8 , din [7:0] $end
$var wire 1 ' rd_wr $end
$var wire 1 ( reset $end
$var wire 1 ) start $end
$var wire 1 * stop $end
$var wire 1 " SDA $end
$var wire 1 # SCL $end
$var parameter 32 - S0 $end
$var parameter 32 . S1 $end
$var parameter 32 / S10 $end
$var parameter 32 0 S11 $end
$var parameter 32 1 S12 $end
$var parameter 32 2 S13 $end
$var parameter 32 3 S14 $end
$var parameter 32 4 S2 $end
$var parameter 32 5 S3 $end
$var parameter 32 6 S4 $end
$var parameter 32 7 S5 $end
$var parameter 32 8 S6 $end
$var parameter 32 9 S7 $end
$var parameter 32 : S8 $end
$var parameter 32 ; S9 $end
$var parameter 32 < address_phase $end
$var parameter 32 = data_phase $end
$var parameter 32 > receiver_mode $end
$var parameter 32 ? sender_mode $end
$var reg 1 @ ack $end
$var reg 3 A count [2:0] $end
$var reg 8 B dout [7:0] $end
$var reg 1 C mode $end
$var reg 1 D scl $end
$var reg 1 E sda $end
$var reg 4 F state [3:0] $end
$var reg 8 G tx_reg [7:0] $end
$upscope $end
$upscope $end
$enddefinitions $end
$comment Show the parameter values. $end
$dumpall
b1 ?
b0 >
b1 =
b0 <
b1001 ;
b1000 :
b111 9
b110 8
b101 7
b100 6
b11 5
b10 4
b1110 3
b1101 2
b1100 1
b1011 0
b1010 /
b1 .
b0 -
$end
#0
$dumpvars
bx G
bx F
xE
xD
xC
bx B
bx A
x@
b0 ,
b0 +
0*
0)
0(
0'
b0 &
0%
b0 $
x#
x"
bx !
$end
#5
1%
#10
0%
1(
#15
1"
1#
b0 !
b0 B
1E
1D
b0 F
b0 A
1%
#20
0%
0(
#25
1%
#30
0%
b10010 &
b10010 ,
b1101 $
b1101 +
1'
1)
#35
b1 F
1%
#40
0%
#45
0"
b11011 G
1C
0E
b10 F
1%
#50
0%
#55
0#
b11 F
0D
1%
#60
0%
#65
1#
b100 F
b1 A
1D
1%
#70
0%
#75
0#
0D
b101 F
1%
#80
0%
#85
1#
1@
1D
1%
#90
0%
#95
b10010 G
b110 F
1%
#100
0%
#105
0#
b111 F
0D
1%
#110
0%
#115
1#
b110 F
b10 A
1D
1%
#120
0%
#125
0#
b111 F
0D
1%
#130
0%
#135
1#
b110 F
b11 A
1D
1%
#140
0%
#145
1"
0#
1E
b111 F
0D
1%
#150
0%
#155
1#
b110 F
b100 A
1D
1%
#160
0%
#165
0"
0#
0E
b111 F
0D
1%
#170
0%
#175
1#
b110 F
b101 A
1D
1%
#180
0%
#185
0#
b111 F
0D
1%
#190
0%
#195
1#
b110 F
b110 A
1D
1%
#200
0%
#205
1"
0#
1E
b111 F
0D
1%
#210
0%
#215
1#
b110 F
b111 A
1D
1%
#220
0%
#225
0"
0#
0E
b111 F
0D
1%
#230
0%
#235
1#
b110 F
b0 A
1D
1%
#240
0%
#245
0#
b111 F
0D
1%
#250
0%
#255
1#
b100 F
b1 A
1D
1%
#260
0%
#265
0#
0D
b101 F
1%
#270
0%
#275
1#
b110 F
1D
1%
#280
0%
#285
0#
b111 F
0D
1%
#290
0%
#295
1#
b110 F
b10 A
1D
1%
#300
0%
#305
0#
b111 F
0D
1%
#310
0%
#315
1#
b110 F
b11 A
1D
1%
#320
0%
#325
1"
0#
1E
b111 F
0D
1%
#330
0%
#335
1#
b110 F
b100 A
1D
1%
#340
0%
#345
0"
0#
0E
b111 F
0D
1%
#350
0%
#355
1#
b110 F
b101 A
1D
1%
#360
0%
#365
0#
b111 F
0D
1%
#370
0%
#375
1#
b110 F
b110 A
1D
1%
#380
0%
#385
1"
0#
1E
b111 F
0D
1%
#390
0%
#395
1#
b110 F
b111 A
1D
1%
#400
0%
#405
0"
0#
0E
b111 F
0D
1%
#410
0%
#415
1#
b110 F
b0 A
1D
1%
#420
0%
#425
0#
b111 F
0D
1%
#430
0%
#435
1#
b100 F
b1 A
1D
1%
#440
0%
#445
0#
0D
b101 F
1%
#450
0%
#455
1#
b110 F
1D
1%
#460
0%
#465
0#
b111 F
0D
1%
#470
0%
#475
1#
b110 F
b10 A
1D
1%
#480
0%
#485
0#
b111 F
0D
1%
#490
0%
#495
1#
b110 F
b11 A
1D
1%
#500
0%
#505
1"
0#
1E
b111 F
0D
1%
#510
0%
#515
1#
b110 F
b100 A
1D
1%
#520
0%
#525
0"
0#
0E
b111 F
0D
1%
#530
0%
#535
1#
b110 F
b101 A
1D
1%
#540
0%
#545
0#
b111 F
0D
1%
#550
0%
#555
1#
b110 F
b110 A
1D
1%
#560
0%
#565
1"
0#
1E
b111 F
0D
1%
#570
0%
#575
1#
b110 F
b111 A
1D
1%
#580
0%
#585
0"
0#
0E
b111 F
0D
1%
#590
0%
#595
1#
b110 F
b0 A
1D
1%
#600
0%
#605
0#
b111 F
0D
1%
#610
0%
#615
1#
b100 F
b1 A
1D
1%
#620
0%
#625
0#
0D
b101 F
1%
#630
0%
#635
1#
b110 F
1D
1%
#640
0%
#645
0#
b111 F
0D
1%
#650
0%
#655
1#
b110 F
b10 A
1D
1%
#660
0%
#665
0#
b111 F
0D
1%
#670
0%
#675
1#
b110 F
b11 A
1D
1%
#680
0%
#685
1"
0#
1E
b111 F
0D
1%
#690
0%
#695
1#
b110 F
b100 A
1D
1%
#700
0%
#705
0"
0#
0E
b111 F
0D
1%
#710
0%
#715
1#
b110 F
b101 A
1D
1%
#720
0%
#725
0#
b111 F
0D
1%
#730
0%
#735
1#
b110 F
b110 A
1D
1%
#740
0%
#745
1"
0#
1E
b111 F
0D
1%
#750
0%
#755
1#
b110 F
b111 A
1D
1%
#760
0%
#765
0"
0#
0E
b111 F
0D
1%
#770
0%
#775
1#
b110 F
b0 A
1D
1%
#780
0%
#785
0#
b111 F
0D
1%
#790
0%
#795
1#
b100 F
b1 A
1D
1%
#800
0%
#805
0#
0D
b101 F
1%
#810
0%
#815
1#
b110 F
1D
1%
#820
0%
#825
0#
b111 F
0D
1%
#830
0%
#835
1#
b110 F
b10 A
1D
1%
#840
0%
#845
0#
b111 F
0D
1%
#850
0%
#855
1#
b110 F
b11 A
1D
1%
#860
0%
#865
1"
0#
1E
b111 F
0D
1%
#870
0%
#875
1#
b110 F
b100 A
1D
1%
#880
0%
#885
0"
0#
0E
b111 F
0D
1%
#890
0%
#895
1#
b110 F
b101 A
1D
1%
#900
0%
#905
0#
b111 F
0D
1%
#910
0%
#915
1#
b110 F
b110 A
1D
1%
#920
0%
#925
1"
0#
1E
b111 F
0D
1%
#930
0%
#935
1#
b110 F
b111 A
1D
1%
#940
0%
#945
0"
0#
0E
b111 F
0D
1%
#950
0%
#955
1#
b110 F
b0 A
1D
1%
#960
0%
#965
0#
b111 F
0D
1%
#970
0%
#975
1#
b100 F
b1 A
1D
1%
#980
0%
#985
0#
0D
b101 F
1%
#990
0%
#995
1#
b110 F
1D
1%
